{
  "run_id": "20260618_123412",
  "source_model": "D:\\_COMSOL_FILE_SAVE_\\COMSOL_Ring_Fountain\\05_two_phase_free_surface\\5B2_static_ring_free_surface_smoke\\models\\ring_fountain_v5B2_3_static_ring_free_surface_boundary_confirmed.mph",
  "summary": {
    "rotating_frame_present": true,
    "rotating_frame_tags": [
      "rtfr1"
    ],
    "gravity_present": true,
    "gravity_tags": [
      "grav1"
    ],
    "wall_features": [
      "wallbc1"
    ],
    "wall_ring_overlap": [
      {
        "feature_tag": "wallbc1",
        "intersects_ring": [
          4,
          5,
          6,
          7
        ],
        "selection_boundaries": [
          2,
          3,
          4,
          5,
          6,
          7,
          8
        ]
      }
    ],
    "physics_types": [
      "LaminarFlow",
      "LevelSet"
    ],
    "feature_types": [
      "AxialSymmetry",
      "Continuity",
      "FluidProperties",
      "Gravity",
      "LevelSetModel",
      "NoFlow",
      "RotatingFrameFD",
      "WallBC",
      "init",
      "initFluid2"
    ],
    "level_set_like_features": [
      "lsm1",
      "init1",
      "initfluid2",
      "axi1",
      "nf1",
      "dcont1"
    ],
    "multiphysics_tags": [],
    "two_phase_coupling_detected": false,
    "rho_mu_definitions_detected_in_variables": false,
    "surface_tension_like_definition_detected": true
  },
  "physics_features": [
    {
      "physics_tag": "spf",
      "physics_type": "LaminarFlow",
      "physics_label": "Laminar Flow",
      "feature_tag": "fp1",
      "feature_type": "FluidProperties",
      "feature_label": "Fluid Properties 1",
      "selection_boundaries": [],
      "intersects_ring": [],
      "active_or_solved": "True",
      "key_properties": {
        "rho": "rho_air+(rho_w-rho_air)*phils",
        "mu": "mu_air+(mu_w-mu_air)*phils",
        "rho_mat": "userdef",
        "mu_mat": "userdef",
        "mu0": "1e-3[Pa*s]",
        "mu0_mat": "from_mat",
        "mu0c": "1e-3[Pa*s]",
        "mu0c_mat": "from_mat",
        "mu0cw": "1e-3[Pa*s]",
        "mu0cw_mat": "from_mat",
        "mu0cy": "1e-3[Pa*s]",
        "mu0cy_mat": "from_mat",
        "mu0e": "1e-3[Pa*s]",
        "mu0e_mat": "from_mat",
        "mu_DK": "1e-3[Pa*s]",
        "mu_DK_mat": "from_mat",
        "mu_inf": "0[Pa*s]",
        "mu_inf_mat": "from_mat",
        "mu_infc": "0[Pa*s]",
        "mu_infc_mat": "from_mat",
        "mu_infcy": "0[Pa*s]",
        "mu_infcy_mat": "from_mat",
        "mu_infs": "0[Pa*s]",
        "mu_infs_mat": "from_mat",
        "mu_init_app": "spf.mu0e",
        "mu_p": "1e-3[Pa*s]",
        "mu_p_mat": "from_mat",
        "mu_pc": "1e-3[Pa*s]",
        "mu_pc_mat": "from_mat"
      },
      "property_names": [
        "MixingLengthLimit",
        "l_mix_lim",
        "LengthScaleSpecification",
        "lref",
        "rho_mat",
        "rho",
        "minput_temperature_src",
        "minput_temperature",
        "editModelInputs",
        "Constitutiverelation",
        "mu_mat",
        "mu",
        "nonNewtonianModels",
        "sr_ref",
        "sr_lowlimit",
        "m_p",
        "mu_init_app",
        "kf",
        "kb",
        "m_y0",
        "m_yt",
        "tau_y0",
        "tau_yt",
        "nb",
        "nf",
        "m_pow_mat",
        "m_pow",
        "n_pow_mat",
        "n_pow",
        "mu0_mat",
        "mu0",
        "mu_inf_mat",
        "mu_inf",
        "lam_car_mat",
        "lam_car",
        "n_car_mat",
        "n_car",
        "mu0cy_mat",
        "mu0cy",
        "mu_infcy_mat",
        "mu_infcy",
        "lam_cy_mat",
        "lam_cy",
        "n_cy_mat",
        "n_cy",
        "a_car_mat",
        "a_car",
        "mu0cw_mat",
        "mu0cw",
        "lam_cw_mat",
        "lam_cw",
        "n_cw_mat",
        "n_cw",
        "mu_p_mat",
        "mu_p",
        "tau_y_mat",
        "tau_y",
        "mu_infs_mat",
        "mu_infs",
        "m_pows_mat",
        "m_pows",
        "n_pows_mat",
        "n_pows",
        "tau_half_mat",
        "tau_half",
        "a_e_mat",
        "a_e",
        "mu0e_mat",
        "mu0e",
        "m_powhb_mat",
        "m_powhb",
        "n_powhb_mat",
        "n_powhb",
        "tau_yhb_mat",
        "tau_yhb",
        "mu_pc_mat",
        "mu_pc",
        "tau_yc_mat",
        "tau_yc",
        "tau_tr_mat",
        "tau_tr",
        "mu0c_mat",
        "mu0c",
        "mu_infc_mat",
        "mu_infc",
        "n_c_mat",
        "n_c",
        "mu_DK_mat",
        "mu_DK",
        "lam_DK_mat",
        "lam_DK",
        "tau_yDK_mat",
        "tau_yDK",
        "m_powrs_mat",
        "m_powrs",
        "n_powrs_mat",
        "n_powrs",
        "tau_yrs_mat",
        "tau_yrs",
        "thermalFunction",
        "Twlf",
        "C1wlf",
        "C2wlf",
        "T0",
        "Q",
        "be",
        "alphaT",
        "shift_temperature_src",
        "shift_temperature",
        "streamlinens",
        "crosswindns",
        "minput_pressure_src",
        "minput_pressure",
        "minput_electricfield_src",
        "minput_electricfield",
        "minput_magneticfield_src",
        "minput_magneticfield",
        "minput_magneticfluxdensity_src",
        "minput_magneticfluxdensity",
        "minput_velocity_src",
        "minput_velocity",
        "minput_frequency_src",
        "minput_frequency",
        "minput_stress_src",
        "minput_stress",
        "minput_effectiveplasticstrain_src",
        "minput_effectiveplasticstrain",
        "minput_strainreferencetemperature_src",
        "minput_strainreferencetemperature",
        "minput_concentration_src",
        "minput_concentration",
        "minput_numberdensity_src",
        "minput_numberdensity",
        "minput_relativehumidity_src",
        "minput_relativehumidity",
        "minput_currentdensity_src",
        "minput_currentdensity",
        "minput_shiftedmagneticfield_src",
        "minput_shiftedmagneticfield",
        "StudyStep",
        "showPhysicsSymbols"
      ]
    },
    {
      "physics_tag": "spf",
      "physics_type": "LaminarFlow",
      "physics_label": "Laminar Flow",
      "feature_tag": "init1",
      "feature_type": "init",
      "feature_label": "Initial Values 1",
      "selection_boundaries": [],
      "intersects_ring": [],
      "active_or_solved": "True",
      "key_properties": {},
      "property_names": [
        "u_init",
        "p_init",
        "nutilde_init",
        "G_init",
        "k_init",
        "ep_init",
        "om_init",
        "yPlus_init",
        "uPlus_init",
        "zeta_init",
        "alpha_init",
        "gamma_init",
        "R_init",
        "CompensateForHydrostaticPressureApproximation",
        "CompensateForHydrostaticPressure",
        "coordinateSystem",
        "StudyStep",
        "showPhysicsSymbols"
      ]
    },
    {
      "physics_tag": "spf",
      "physics_type": "LaminarFlow",
      "physics_label": "Laminar Flow",
      "feature_tag": "axi1",
      "feature_type": "AxialSymmetry",
      "feature_label": "Axial Symmetry 1",
      "selection_boundaries": [
        1
      ],
      "intersects_ring": [],
      "active_or_solved": "True",
      "key_properties": {},
      "property_names": [
        "constraintOptions",
        "constraintType",
        "constraintMethod",
        "StudyStep",
        "showPhysicsSymbols"
      ]
    },
    {
      "physics_tag": "spf",
      "physics_type": "LaminarFlow",
      "physics_label": "Laminar Flow",
      "feature_tag": "wallbc1",
      "feature_type": "WallBC",
      "feature_label": "Wall 1",
      "selection_boundaries": [
        2,
        3,
        4,
        5,
        6,
        7,
        8
      ],
      "intersects_ring": [
        4,
        5,
        6,
        7
      ],
      "active_or_solved": "True",
      "key_properties": {
        "BoundaryCondition": "NoSlip",
        "SlidingWall": "0",
        "TranslationalVelocityOption": "AutomaticFromFrame",
        "utr": "0",
        "ApplyWallRoughness": "0",
        "epsilonr": "80",
        "mueo": "7e-8[m^2/(V*s)]",
        "sigmat": "0.75"
      },
      "property_names": [
        "BoundaryCondition",
        "uleak",
        "UseViscousSlip",
        "UseThermalCreep",
        "SlipLengthOption",
        "Ls",
        "alphav",
        "lambda",
        "sigmat",
        "ElectroosmoticOption",
        "mueo",
        "zeta",
        "epsilonr",
        "T_src",
        "T",
        "E_src",
        "E",
        "utr",
        "uvw",
        "vw",
        "SlidingWall",
        "TranslationalVelocityOption",
        "constraintOptions",
        "constraintType",
        "constraintMethod",
        "ApplyWallRoughness",
        "RoughnessModel",
        "kseq",
        "ks",
        "Cs",
        "NavierSlip",
        "beta",
        "beta_factor",
        "tau_ref",
        "m",
        "IncludeUtrInNavierSlipForce",
        "tau_y",
        "k1",
        "k2",
        "StudyStep",
        "showPhysicsSymbols",
        "pairContrib"
      ]
    },
    {
      "physics_tag": "spf",
      "physics_type": "LaminarFlow",
      "physics_label": "Laminar Flow",
      "feature_tag": "grav1",
      "feature_type": "Gravity",
      "feature_label": "Gravity 1",
      "selection_boundaries": [],
      "intersects_ring": [],
      "active_or_solved": "False",
      "key_properties": {
        "g": "0",
        "projectGravity": "1"
      },
      "property_names": [
        "g",
        "projectGravity",
        "StudyStep",
        "showPhysicsSymbols"
      ]
    },
    {
      "physics_tag": "spf",
      "physics_type": "LaminarFlow",
      "physics_label": "Laminar Flow",
      "feature_tag": "rtfr1",
      "feature_type": "RotatingFrameFD",
      "feature_label": "Rotating Frame 1",
      "selection_boundaries": [],
      "intersects_ring": [],
      "active_or_solved": "False",
      "key_properties": {
        "AxisOfRotation": "zAxis",
        "RotationalDirection": "CounterClockwise",
        "RotationalFrequency": "AngularVelocity"
      },
      "property_names": [
        "AxisOfRotation",
        "RotationalDirection",
        "RotationalFrequency",
        "Ovm",
        "rpt",
        "alpha",
        "StudyStep",
        "showPhysicsSymbols"
      ]
    },
    {
      "physics_tag": "spf",
      "physics_type": "LaminarFlow",
      "physics_label": "Laminar Flow",
      "feature_tag": "dcont1",
      "feature_type": "Continuity",
      "feature_label": "Flow Continuity 1",
      "selection_boundaries": [],
      "intersects_ring": [],
      "active_or_solved": "False",
      "key_properties": {},
      "property_names": [
        "continuityConditions",
        "pressureLossModel",
        "K_expansion_loss",
        "K_contraction_loss",
        "venaContractaModel",
        "c_vc",
        "c_vc_ll",
        "n_vc",
        "kJumpnPLossInclude",
        "K_k_conversion",
        "epJumpPLossInclude",
        "K_ep_conversion",
        "omJumpPLossInclude",
        "K_om_conversion",
        "constraintOptions",
        "constraintType",
        "constraintMethod",
        "pairSelection",
        "pairs",
        "pairsList",
        "pairDisconnect",
        "StudyStep",
        "showPhysicsSymbols"
      ]
    },
    {
      "physics_tag": "ls",
      "physics_type": "LevelSet",
      "physics_label": "Level Set",
      "feature_tag": "lsm1",
      "feature_type": "LevelSetModel",
      "feature_label": "Level Set Model 1",
      "selection_boundaries": [],
      "intersects_ring": [],
      "active_or_solved": "True",
      "key_properties": {
        "epsilon_ls": "ls.ep_default",
        "gamma": "1"
      },
      "property_names": [
        "gamma",
        "epsilon_ls",
        "u_src",
        "u",
        "StudyStep",
        "showPhysicsSymbols"
      ]
    },
    {
      "physics_tag": "ls",
      "physics_type": "LevelSet",
      "physics_label": "Level Set",
      "feature_tag": "init1",
      "feature_type": "init",
      "feature_label": "Initial Values 1",
      "selection_boundaries": [],
      "intersects_ring": [],
      "active_or_solved": "True",
      "key_properties": {},
      "property_names": [
        "InitialValuesOption",
        "phils_init",
        "FluidInDomain",
        "StudyStep",
        "showPhysicsSymbols"
      ]
    },
    {
      "physics_tag": "ls",
      "physics_type": "LevelSet",
      "physics_label": "Level Set",
      "feature_tag": "initfluid2",
      "feature_type": "initFluid2",
      "feature_label": "Initial Values, Fluid 2",
      "selection_boundaries": [],
      "intersects_ring": [],
      "active_or_solved": "True",
      "key_properties": {},
      "property_names": [
        "InitialValuesOption",
        "phils_init",
        "FluidInDomain",
        "StudyStep",
        "showPhysicsSymbols"
      ]
    },
    {
      "physics_tag": "ls",
      "physics_type": "LevelSet",
      "physics_label": "Level Set",
      "feature_tag": "axi1",
      "feature_type": "AxialSymmetry",
      "feature_label": "Axial Symmetry 1",
      "selection_boundaries": [
        1
      ],
      "intersects_ring": [],
      "active_or_solved": "True",
      "key_properties": {},
      "property_names": [
        "StudyStep"
      ]
    },
    {
      "physics_tag": "ls",
      "physics_type": "LevelSet",
      "physics_label": "Level Set",
      "feature_tag": "nf1",
      "feature_type": "NoFlow",
      "feature_label": "No Flow 1",
      "selection_boundaries": [
        2,
        3,
        4,
        5,
        6,
        7,
        8
      ],
      "intersects_ring": [
        4,
        5,
        6,
        7
      ],
      "active_or_solved": "True",
      "key_properties": {},
      "property_names": [
        "StudyStep",
        "showPhysicsSymbols",
        "pairContrib"
      ]
    },
    {
      "physics_tag": "ls",
      "physics_type": "LevelSet",
      "physics_label": "Level Set",
      "feature_tag": "dcont1",
      "feature_type": "Continuity",
      "feature_label": "Continuity 1",
      "selection_boundaries": [],
      "intersects_ring": [],
      "active_or_solved": "False",
      "key_properties": {},
      "property_names": [
        "pairSelection",
        "pairs",
        "pairsList",
        "pairDisconnect",
        "StudyStep",
        "showPhysicsSymbols"
      ]
    }
  ],
  "multiphysics": [],
  "variables": []
}